{
  "project_info": {
    "project_number": "927589564155",
    "project_id": "remoteassist-f9895",
    "storage_bucket": "remoteassist-f9895.appspot.com"
  },
  "client": [
    {
      "client_info": {
        "mobilesdk_app_id": "1:927589564155:android:64b47b75742ea292a17a5e",
        "android_client_info": {
          "package_name": "com.example.screenshotapp"
        }
      },
      "oauth_client": [
        {
          "client_id": "927589564155-h01vuv83fhqu1bo5lmrb01r328jdp94g.apps.googleusercontent.com",
          "client_type": 3
        }
      ],
      "api_key": [
        {
          "current_key": "AIzaSyBklatv1wkXHdStcMu7MpjTZRwg9x46W48"
        }
      ],
      "services": {
        "appinvite_service": {
          "other_platform_oauth_client": [
            {
              "client_id": "927589564155-h01vuv83fhqu1bo5lmrb01r328jdp94g.apps.googleusercontent.com",
              "client_type": 3
            }
          ]
        }
      }
    }
  ],
  "configuration_version": "1"
}